.coveragerc
.gitignore
CHANGELOG.rst
LICENSE.txt
MANIFEST.in
Makefile
README.rst
nose.cfg
setup.cfg
setup.py
aioari/__init__.py
aioari/client.py
aioari/model.py
aioari.egg-info/PKG-INFO
aioari.egg-info/SOURCES.txt
aioari.egg-info/dependency_links.txt
aioari.egg-info/requires.txt
aioari.egg-info/top_level.txt
examples/bridge_example.py
examples/cleanup_example.py
examples/example.py
examples/originate_example.py
examples/playback_example.py
sample-api/README.md
sample-api/applications.json
sample-api/asterisk.json
sample-api/bridges.json
sample-api/channels.json
sample-api/deviceStates.json
sample-api/endpoints.json
sample-api/events.json
sample-api/mailboxes.json
sample-api/playbacks.json
sample-api/recordings.json
sample-api/resources.json
sample-api/sounds.json
tests/__init__.py
tests/client_test.py
tests/conftest.py
tests/utils.py
tests/websocket_test.py