Metadata-Version: 1.1
Name: aioari
Version: 0.10.2
Summary: Asynchronous library for accessing the Asterisk REST Interface
Home-page: https://github.com/M-o-a-T/aioari
Author: Matthias Urlichs
Author-email: matthias@urlichs.de
License: BSD 3-Clause License
Platform: UNKNOWN
Classifier: Development Status :: 4 - Beta
Classifier: Intended Audience :: Developers
Classifier: Topic :: Communications :: Telephony
Classifier: Topic :: Software Development :: Libraries :: Python Modules
Classifier: License :: OSI Approved :: BSD License
Classifier: Operating System :: OS Independent
Classifier: Programming Language :: Python :: 3.5
Classifier: Programming Language :: Python :: 3.6
